README.rst
setup.cfg
setup.py
cursesrace/__init__.py
cursesrace.egg-info/PKG-INFO
cursesrace.egg-info/SOURCES.txt
cursesrace.egg-info/dependency_links.txt
cursesrace.egg-info/entry_points.txt
cursesrace.egg-info/not-zip-safe
cursesrace.egg-info/top_level.txt