Metadata-Version: 1.0
Name: cursesrace
Version: 0.0.3
Summary: An ncurses example: RACE
Home-page: http://github.com/storborg/cursesrace
Author: Scott Torborg
Author-email: storborg@gmail.com
License: MIT
Platform: UNKNOWN
